logstream/__init__.py
logstream/logstream.py
logstream/test.py
logstream_ua-0.1.dist-info/LICENSE
logstream_ua-0.1.dist-info/METADATA
logstream_ua-0.1.dist-info/WHEEL
logstream_ua-0.1.dist-info/top_level.txt
logstream_ua-0.1.dist-info/RECORD
