Metadata-Version: 2.1
Name: logstream-ua
Version: 0.1
Summary: Logger Tool
Home-page: https://github.com/gods-created/logstream-ua
Author: Bohdan Terskow
Author-email: bohdanterskow@gmail.com
Keywords: python,logs,loguru,log,logstream,error,debug,info,fatal,warning
Classifier: Development Status :: 1 - Planning
Classifier: Intended Audience :: Developers
Classifier: Programming Language :: Python :: 3
Classifier: Operating System :: Unix
Classifier: Operating System :: MacOS :: MacOS X
Classifier: Operating System :: Microsoft :: Windows
License-File: LICENSE
Requires-Dist: loguru
